LICENSE
MANIFEST.in
README.rst
requirements.txt
setup.cfg
setup.py
nlppln/__init__.py
nlppln/copycwl.py
nlppln/utils.py
nlppln/wfgenerator.py
nlppln.egg-info/PKG-INFO
nlppln.egg-info/SOURCES.txt
nlppln.egg-info/dependency_links.txt
nlppln.egg-info/entry_points.txt
nlppln.egg-info/requires.txt
nlppln.egg-info/top_level.txt
nlppln/commands/__init__.py
nlppln/commands/apachetika.py
nlppln/commands/archive2dir.py
nlppln/commands/basic_text_statistics.py
nlppln/commands/check_utf8.py
nlppln/commands/clear_xml_elements.py
nlppln/commands/copy_and_rename.py
nlppln/commands/create_chunked_list.py
nlppln/commands/delete_empty_files.py
nlppln/commands/filter_nes.py
nlppln/commands/flatten_list.py
nlppln/commands/freqs.py
nlppln/commands/frog_to_saf.py
nlppln/commands/liwc_tokenized.py
nlppln/commands/lowercase.py
nlppln/commands/ls.py
nlppln/commands/ls_chunk.py
nlppln/commands/ls_dirs.py
nlppln/commands/merge_csv.py
nlppln/commands/normalize_whitespace_punctuation.py
nlppln/commands/prettify_xml.py
nlppln/commands/remove_newlines.py
nlppln/commands/remove_xml_elements.py
nlppln/commands/replace_ner.py
nlppln/commands/saf_to_freqs.py
nlppln/commands/saf_to_txt.py
nlppln/commands/save_ner_data.py
nlppln/commands/spacy.py
nlppln/commands/xml_to_text.py
nlppln/cwl/anonymize.cwl
nlppln/cwl/apachetika.cwl
nlppln/cwl/archive2dir.cwl
nlppln/cwl/basic-text-statistics.cwl
nlppln/cwl/cat.cwl
nlppln/cwl/check-utf8.cwl
nlppln/cwl/clear-xml-elements.cwl
nlppln/cwl/copy-and-rename.cwl
nlppln/cwl/create-chunked-list.cwl
nlppln/cwl/delete-empty-files.cwl
nlppln/cwl/filter-nes.cwl
nlppln/cwl/flatten-dirs.cwl
nlppln/cwl/flatten-list.cwl
nlppln/cwl/freqs.cwl
nlppln/cwl/frog-dir.cwl
nlppln/cwl/frog-single-text.cwl
nlppln/cwl/frog-to-saf.cwl
nlppln/cwl/gather-dirs.cwl
nlppln/cwl/ixa-pipe-tok.cwl
nlppln/cwl/liwc-tokenized.cwl
nlppln/cwl/lowercase.cwl
nlppln/cwl/ls-dirs.cwl
nlppln/cwl/ls.cwl
nlppln/cwl/ls_chunk.cwl
nlppln/cwl/merge-csv.cwl
nlppln/cwl/merge-yaml.cwl
nlppln/cwl/mkdir.cwl
nlppln/cwl/normalize-whitespace-punctuation.cwl
nlppln/cwl/prettify-xml.cwl
nlppln/cwl/remove-newlines.cwl
nlppln/cwl/remove-xml-elements.cwl
nlppln/cwl/replace-ner.cwl
