Metadata-Version: 1.1
Name: nlppln
Version: 0.3.3
Summary: NLP pipeline software using common workflow language
Home-page: https://github.com/nlppln/nlppln
Author: Janneke van der Zwaan
Author-email: j.vanderzwaan@esciencecenter.nl
License: Apache
Keywords: text-mining,nlp,pipeline
Platform: UNKNOWN
Classifier: Development Status :: 3 - Alpha
Classifier: Intended Audience :: Developers
Classifier: License :: OSI Approved :: Apache Software License
Classifier: Programming Language :: Python :: 2
Classifier: Programming Language :: Python :: 2.7
Classifier: Programming Language :: Python :: 3
Classifier: Programming Language :: Python :: 3.4
Classifier: Programming Language :: Python :: 3.5
Classifier: Programming Language :: Python :: 3.6
